{
  "last_update": "2025-10-10T16:55:13.452833+00:00",
  "channels": [
    {
      "tvg-id": "ptvpk",
      "tvg-logo": "https://i.imgur.com/bmk7yJs.png",
      "name": "PTV Sports",
      "url": "https://d15.epicquesthero.com:999/hls/ptvpk.m3u8?md5=z4ujY7IY0_BTZQq8pwoGyQ&expires=1760122469"
    },
    {
      "tvg-id": "sonyten1",
      "tvg-logo": "https://i.imgur.com/bmk7yJs.png",
      "name": "Tony Sports 1",
      "url": "https://d15.epicquesthero.com:999/hls/ten1hd.m3u8?md5=snIobYVKeb_158P8fRvixg&expires=1760122469"
    },
    {
      "tvg-id": "willowusa",
      "tvg-logo": "https://i.imgur.com/bmk7yJs.png",
      "name": "Willow Cricket",
      "url": "https://d15.epicquesthero.com:999/hls/willowusa.m3u8?md5=uEpGMNv76MJd0DOCnr-HMQ&expires=1760122469"
    },
    {
      "tvg-id": "tensp",
      "tvg-logo": "https://i.imgur.com/bmk7yJs.png",
      "name": "Ten Sports PK",
      "url": "https://d15.epicquesthero.com:999/hls/tenspk.m3u8?md5=WKdoOQfTdV1rFsEIvYe-0Q&expires=1760122469"
    },
    {
      "tvg-id": "asportshd",
      "tvg-logo": "https://i.imgur.com/bmk7yJs.png",
      "name": "A Sports HD",
      "url": "https://d15.epicquesthero.com:999/hls/asportshd.m3u8?md5=C1tgDl3z4l3aWXpKSlxs-g&expires=1760122469"
    },
    {
      "tvg-id": "tonymax",
      "tvg-logo": "https://i.imgur.com/bmk7yJs.png",
      "name": "Tony Sports 3",
      "url": "https://d15.epicquesthero.com:999/hls/sonyespnind.m3u8?md5=4zrVyPTcsyzk_lbYa5DYLA&expires=1760122469"
    },
    {
      "tvg-id": "sscricket",
      "tvg-logo": "https://i.imgur.com/bmk7yJs.png",
      "name": "Super Cricket",
      "url": "https://d15.epicquesthero.com:999/hls/supercricket.m3u8?md5=z2UqymfICJY8kGgWETViag&expires=1760122469"
    },
    {
      "tvg-id": "skys2",
      "tvg-logo": "https://i.imgur.com/bmk7yJs.png",
      "name": "Sky Sports Cricket",
      "url": "https://d15.epicquesthero.com:999/hls/skyscric.m3u8?md5=gP61XUXrBhM-si4Yqesxpg&expires=1760122470"
    },
    {
      "tvg-id": "btsp4",
      "tvg-logo": "https://i.imgur.com/bmk7yJs.png",
      "name": "BT Sports 4",
      "url": "https://d15.epicquesthero.com:999/hls/bbtespn.m3u8?md5=eY489tuJeXdXKCjquFdmQA&expires=1760122469"
    },
    {
      "tvg-id": "btsp3",
      "tvg-logo": "https://i.imgur.com/bmk7yJs.png",
      "name": "BT Sports 3",
      "url": "https://d15.epicquesthero.com:999/hls/bbtsp3.m3u8?md5=D7oqBV-PXILHWYyEVNv43w&expires=1760122469"
    },
    {
      "tvg-id": "btsp1",
      "tvg-logo": "https://i.imgur.com/bmk7yJs.png",
      "name": "BT Sports 1",
      "url": "https://d15.epicquesthero.com:999/hls/bbtsp1.m3u8?md5=qT5AkdfS7BvcazOoYVy2MA&expires=1760122469"
    },
    {
      "tvg-id": "btsp2",
      "tvg-logo": "https://i.imgur.com/bmk7yJs.png",
      "name": "BT Sports 2",
      "url": "https://d15.epicquesthero.com:999/hls/bbtsp2.m3u8?md5=CoLZ34gCnxfJxH8n1JpoUQ&expires=1760122469"
    },
    {
      "tvg-id": "willowextra",
      "tvg-logo": "https://i.imgur.com/bmk7yJs.png",
      "name": "Willow 2",
      "url": "https://d15.epicquesthero.com:999/hls/willowextra.m3u8?md5=_kbjHmcIcp7ZJk0VqoVrIg&expires=1760122469"
    },
    {
      "tvg-id": "fox501",
      "tvg-logo": "https://i.imgur.com/bmk7yJs.png",
      "name": "FOX Cricket 501",
      "url": "https://d15.epicquesthero.com:999/hls/fox501.m3u8?md5=00TVzGs2cWs7sXMCEz52gQ&expires=1760122470"
    },
    {
      "tvg-id": "skys1",
      "tvg-logo": "https://i.imgur.com/bmk7yJs.png",
      "name": "Sky Sports Main Event",
      "url": "https://d15.epicquesthero.com:999/hls/skysme.m3u8?md5=sZJaoGPgwIvakO-xKTZWAQ&expires=1760122470"
    },
    {
      "tvg-id": "viasp1",
      "tvg-logo": "https://i.imgur.com/bmk7yJs.png",
      "name": "Via Play Sports 1",
      "url": "https://d15.epicquesthero.com:999/hls/premieruk.m3u8?md5=k7cs5roAzszrlcuKHxyunQ&expires=1760122469"
    },
    {
      "tvg-id": "btsp5",
      "tvg-logo": "https://i.imgur.com/bmk7yJs.png",
      "name": "BT Sports 5",
      "url": "https://d15.epicquesthero.com:999/hls/hdchnl10.m3u8?md5=PluBJC_1-BZrxqLFuRfFYg&expires=1760122469"
    },
    {
      "tvg-id": "tara",
      "tvg-logo": "https://i.imgur.com/bmk7yJs.png",
      "name": " Tara Sports 1",
      "url": "https://d15.epicquesthero.com:999/hls/star1in.m3u8?md5=yscfF6DWz43Y5MxAAfjHcw&expires=1760122469"
    },
    {
      "tvg-id": "tara1hi",
      "tvg-logo": "https://i.imgur.com/bmk7yJs.png",
      "name": " Tara Sports Hindi",
      "url": "https://d15.epicquesthero.com:999/hls/starhindi.m3u8?md5=-1pNyQeQq9KVL1bXgZU4VQ&expires=1760122469"
    },
    {
      "tvg-id": "sky1nz",
      "tvg-logo": "https://i.imgur.com/bmk7yJs.png",
      "name": " Sky Sport 1 NZ",
      "url": "https://d15.epicquesthero.com:999/hls/sky1nz.m3u8?md5=PGYfUOyeqiWHDZt_gPIouw&expires=1760122469"
    },
    {
      "tvg-id": "sky2nz",
      "tvg-logo": "https://i.imgur.com/bmk7yJs.png",
      "name": " Sky Sport 2 NZ",
      "url": "https://d15.epicquesthero.com:999/hls/sky2nz.m3u8?md5=Gn0tHFTaRR5r-FwUHoajgQ&expires=1760122469"
    },
    {
      "tvg-id": "sky3nz",
      "tvg-logo": "https://i.imgur.com/bmk7yJs.png",
      "name": " Sky Sport 3 NZ",
      "url": "https://d15.epicquesthero.com:999/hls/sky3nz.m3u8?md5=naW3MnV1_fdg3EU-sHrhFQ&expires=1760122469"
    },
    {
      "tvg-id": "sky4nz",
      "tvg-logo": "https://i.imgur.com/bmk7yJs.png",
      "name": " Sky Sport 4 NZ",
      "url": "https://d15.epicquesthero.com:999/hls/sky4nz.m3u8?md5=mGMfhhufz8aei20pgwFuBA&expires=1760122469"
    },
    {
      "tvg-id": "sky5nz",
      "tvg-logo": "https://i.imgur.com/bmk7yJs.png",
      "name": " Sky Sport 5 NZ",
      "url": "https://d15.epicquesthero.com:999/hls/sky5nz.m3u8?md5=g-2Jtoq-BJbZWa-lsWil3w&expires=1760122469"
    },
    {
      "tvg-id": "sky6nz",
      "tvg-logo": "https://i.imgur.com/bmk7yJs.png",
      "name": " Sky Sport 6 NZ",
      "url": "https://d15.epicquesthero.com:999/hls/sky6nz.m3u8?md5=RKLQoxUMvXQ9-EpBZTTTpg&expires=1760122469"
    },
    {
      "tvg-id": "sky7nz",
      "tvg-logo": "https://i.imgur.com/bmk7yJs.png",
      "name": " Sky Sport 7 NZ",
      "url": "https://d15.epicquesthero.com:999/hls/sky7nz.m3u8?md5=-Wsxd3g8qHh0PFaiDjwAbA&expires=1760122469"
    },
    {
      "tvg-id": "sky8nz",
      "tvg-logo": "https://i.imgur.com/bmk7yJs.png",
      "name": " Sky Sport 8 NZ",
      "url": "https://d15.epicquesthero.com:999/hls/sky8nz.m3u8?md5=lrU6uQieQoMr2mSSPqRsmQ&expires=1760122469"
    },
    {
      "tvg-id": "laligauk",
      "tvg-logo": "https://i.imgur.com/bmk7yJs.png",
      "name": "LaLiga UK",
      "url": "https://d15.epicquesthero.com:999/hls/laligauk.m3u8?md5=dmjsymHbJSqu_J_vBO45uA&expires=1760122469"
    },
    {
      "tvg-id": "skysfotb",
      "tvg-logo": "https://i.imgur.com/bmk7yJs.png",
      "name": " Sky Sports Football",
      "url": "https://d15.epicquesthero.com:999/hls/skysfott.m3u8?md5=uWm1aZqhZSqiWtDlpP0r9w&expires=1760122469"
    },
    {
      "tvg-id": "hdchnl2",
      "tvg-logo": "https://i.imgur.com/bmk7yJs.png",
      "name": " Premier Sports 2",
      "url": null
    }
  ]
}